qnp/__init__.py
qnp/Database/__init__.py
qnp/Database/RefractiveIndexDatabase/RefractiveIndexDatabase.py
qnp/Database/RefractiveIndexDatabase/__init__.py
qnp/Database/RefractiveIndexDatabase/utils.py
qnp/Physics/Constants.py
qnp/Physics/Functions.py
qnp/Physics/__init__.py
qnp/Ploter/Ploter.py
qnp/Ploter/__init__.py
qnp-0.1.13.dist-info/METADATA
qnp-0.1.13.dist-info/WHEEL
qnp-0.1.13.dist-info/RECORD
